ondc_cryptic_utils/__init__.py
ondc_cryptic_utils/cryptic_util.py
ondc_cryptic_utils-0.0.1.dist-info/licenses/LICENSE
ondc_cryptic_utils-0.0.1.dist-info/METADATA
ondc_cryptic_utils-0.0.1.dist-info/WHEEL
ondc_cryptic_utils-0.0.1.dist-info/top_level.txt
ondc_cryptic_utils-0.0.1.dist-info/RECORD
