Metadata-Version: 2.4
Name: ondc-cryptic-utils
Version: 0.0.1
Summary: Cryptographic utilities for ONDC protocol - signing, verification, encryption and authorization header management
Home-page: https://github.com/PShravan/ondc-cryptic-utils
Author: Shravan
Author-email: shravan.nani18@gmail.com
Project-URL: Bug Reports, https://github.com/PShravan/ondc-cryptic-utils/issues
Project-URL: Source, https://github.com/PShravan/ondc-cryptic-utils
Keywords: ondc,cryptography,digital-signatures,encryption,ed25519,x25519
Classifier: Intended Audience :: Developers
Classifier: Topic :: Software Development :: Libraries :: Python Modules
Classifier: Topic :: Security :: Cryptography
Classifier: Topic :: Internet :: WWW/HTTP
Classifier: Programming Language :: Python :: 3
Classifier: Programming Language :: Python :: 3.6
Classifier: Programming Language :: Python :: 3.7
Classifier: Programming Language :: Python :: 3.8
Classifier: Programming Language :: Python :: 3.9
Classifier: Programming Language :: Python :: 3.10
Classifier: Programming Language :: Python :: 3.11
Classifier: Programming Language :: Python :: 3.12
Classifier: Programming Language :: Python :: 3.13
Classifier: License :: OSI Approved :: MIT License
Classifier: Operating System :: OS Independent
Requires-Python: >=3.6
License-File: LICENSE
Requires-Dist: pycryptodomex>=3.20.0
Requires-Dist: cryptography>=41.0.0
Requires-Dist: PyNaCl>=1.5.0
Provides-Extra: dev
Requires-Dist: pytest>=6.0; extra == "dev"
Requires-Dist: pytest-cov; extra == "dev"
Requires-Dist: black; extra == "dev"
Requires-Dist: flake8; extra == "dev"
Requires-Dist: mypy; extra == "dev"
Provides-Extra: test
Requires-Dist: pytest>=6.0; extra == "test"
Requires-Dist: pytest-cov; extra == "test"
Dynamic: license-file
